syncademy/__init__.py
syncademy/config.py
syncademy/main.py
syncademy/bot/__init__.py
syncademy/bot/discord_bot.py
syncademy/cogs/__init__.py
syncademy/cogs/events.py
syncademy/cogs/googlesheet.py
syncademy/cogs/syncademy.py
syncademy/resources/credentials_example.json
syncademy/resources/syncademy_bot_example.ini
syncademy/utilities/__init__.py
syncademy/utilities/course.py
syncademy/utilities/signup.py
syncademy/utilities/student.py
syncademy/utilities/syncademy_emoji.py
syncademy/utilities/syncademy_emoji_converter.py
syncademy/utilities/syncademy_role.py
syncademy/utilities/timeslot.py
syncademy/utilities/timeslot_emoji.py
syncademy_bot-1.6.0.data/data/resources/credentials_example.json
syncademy_bot-1.6.0.data/data/resources/syncademy_bot_example.ini
syncademy_bot-1.6.0.dist-info/LICENSE
syncademy_bot-1.6.0.dist-info/METADATA
syncademy_bot-1.6.0.dist-info/WHEEL
syncademy_bot-1.6.0.dist-info/top_level.txt
syncademy_bot-1.6.0.dist-info/RECORD
